votoutils/_version.py
votoutils/ad2cp/ad2cp_file_move.py
votoutils/ad2cp/ad2cp_nc_clean.py
votoutils/ad2cp/ad2cp_proc.py
votoutils/alerts/al.mp3
votoutils/alerts/alert.sh
votoutils/alerts/env_sound.yml
votoutils/alerts/waker.sh
votoutils/alerts/wakeywakey.py
votoutils/ctd/ctd.py
votoutils/fixers/file_operations.py
votoutils/fixers/fix_adcp_times.py
votoutils/fixers/fix_bad_payload.py
votoutils/fixers/update_meta.py
votoutils/fixers/update_meta.sh
votoutils/glider/convert_to_og1.py
votoutils/glider/fix_chla.py
votoutils/glider/make_og1.py
votoutils/glider/metocc.py
votoutils/glider/post_process_ctd.py
votoutils/glider/post_process_dataset.py
votoutils/glider/post_process_optics.py
votoutils/glider/process_pyglider.py
votoutils/monitor/check_pipeline.py
votoutils/monitor/erddap_checks.py
votoutils/monitor/glider_list.sh
votoutils/monitor/mission_list.sh
votoutils/monitor/mission_stats.py
votoutils/monitor/office_check_glider_files.py
votoutils/monitor/summary_proc_time.py
votoutils/qc/flag_qartod.py
votoutils/sailbuoy/sailbuoy_raw_to_nc.py
votoutils/upload/mailer.sh
votoutils/upload/send_to_erddap.sh
votoutils/upload/send_to_erddap_adcp.sh
votoutils/upload/smhi_download.sh
votoutils/upload/sync_functions.py
votoutils/upload/upload.sh
votoutils/upload/upload_adcp.sh
votoutils/utilities/geocode.py
votoutils/utilities/utilities.py
votoutils/utilities/vocabularies.py
votoutils-0.0.1a2.dist-info/LICENSE
votoutils-0.0.1a2.dist-info/METADATA
votoutils-0.0.1a2.dist-info/WHEEL
votoutils-0.0.1a2.dist-info/top_level.txt
votoutils-0.0.1a2.dist-info/RECORD
