Metadata-Version: 2.1
Name: votoutils
Version: 0.0.1a2
Summary: Utility scripts for VOTO processing
Maintainer-email: Callum Rollo <c.rollo@outlook.com>
License: MIT License
Project-URL: documentation, https://github.com/voto-ocean-knowledge/votoutils
Project-URL: homepage, https://github.com/voto-ocean-knowledge/votoutils
Project-URL: repository, https://github.com/voto-ocean-knowledge/votoutils
Classifier: Programming Language :: Python :: 3 :: Only
Classifier: Programming Language :: Python :: 3.10
Classifier: Programming Language :: Python :: 3.11
Classifier: Programming Language :: Python :: 3.12
Requires-Python: >=3.10
License-File: LICENSE
Requires-Dist: cfgrib
Requires-Dist: dateparser
Requires-Dist: erddapy
Requires-Dist: geopandas>=1.0.0
Requires-Dist: gsw
Requires-Dist: httpx
Requires-Dist: ioos-qc
Requires-Dist: ipython
Requires-Dist: matplotlib
Requires-Dist: netcdf4
Requires-Dist: numpy
Requires-Dist: pandas
Requires-Dist: polars>=1.0.0
Requires-Dist: pynmea2
Requires-Dist: pyyaml
Requires-Dist: seabird
Requires-Dist: xarray
